asposehtmlcloud/__init__.py
asposehtmlcloud/alias.py
asposehtmlcloud/api_client.py
asposehtmlcloud/configuration.py
asposehtmlcloud/rest.py
asposehtmlcloud/api/__init__.py
asposehtmlcloud/api/html_api.py
asposehtmlcloud/api/storage_api.py
asposehtmlcloud/models/__init__.py
asposehtmlcloud/models/base_model.py
asposehtmlcloud/models/conversion_request.py
asposehtmlcloud/models/conversion_result.py
asposehtmlcloud/models/disc_usage.py
asposehtmlcloud/models/error.py
asposehtmlcloud/models/error_details.py
asposehtmlcloud/models/file_version.py
asposehtmlcloud/models/file_versions.py
asposehtmlcloud/models/files_list.py
asposehtmlcloud/models/files_upload_result.py
asposehtmlcloud/models/object_exist.py
asposehtmlcloud/models/storage_exist.py
asposehtmlcloud/models/storage_file.py
test/__init__.py
test/test_helper.py
test/test_html_api.py
test/test_md_api.py
test/test_mhtml_api.py
test/test_storage_api.py
test/test_storage_models.py
test/test_svg_api.py
test/test_trace_api.py
test/test_vectorization_api.py
asposehtmlcloud-22.12.1.dist-info/LICENSE.txt
asposehtmlcloud-22.12.1.dist-info/METADATA
asposehtmlcloud-22.12.1.dist-info/WHEEL
asposehtmlcloud-22.12.1.dist-info/top_level.txt
asposehtmlcloud-22.12.1.dist-info/RECORD
