Metadata-Version: 2.1
Name: asposehtmlcloud
Version: 22.12.1
Summary: Aspose.HTML for Cloud Python SDK
Home-page: https://github.com/aspose-html-cloud/aspose-html-cloud-python
Author: Aspose
Author-email: alexander.makogon@aspose.com
License: MIT
Keywords: html2pdf,epub2pdf,md2html,html2md,html2img,html2xps,epub2xps,convert
Classifier: Development Status :: 5 - Production/Stable
Classifier: Intended Audience :: Developers
Classifier: Topic :: Software Development :: Libraries :: Python Modules
Classifier: License :: OSI Approved :: MIT License
Classifier: Programming Language :: Python :: 2.7
Classifier: Programming Language :: Python :: 3
Classifier: Programming Language :: Python :: 3.4
Classifier: Programming Language :: Python :: 3.5
Classifier: Programming Language :: Python :: 3.6
Classifier: Programming Language :: Python :: 3.7
Classifier: Programming Language :: Python :: 3.8
License-File: LICENSE.txt
Requires-Dist: urllib3 (>=1.15)
Requires-Dist: six (>=1.10)
Requires-Dist: certifi
Requires-Dist: pyopenssl
Requires-Dist: urllib3[secure]
Requires-Dist: python-dateutil
Requires-Dist: requests[security]
